{"events":[{"title":"Test","image":"https://www.google.com/imgres?imgurl=https%3A%2F%2Fwww.memoiresevents.com%2Fwp-content%2Fuploads%2F2022%2F11%2F220313_G40_decor-1-1024x647-1.jpeg&tbnid=0r-bbXzkcKdEkM&vet=12ahUKEwj_19nuvvaBAxWuUbgEHQYQBs0QMygOegQIARBp..i&imgrefurl=https%3A%2F%2Fwww.memoiresevents.com%2F&docid=CK47rDPF627qqM&w=1024&h=647&q=event&ved=2ahUKEwj_19nuvvaBAxWuUbgEHQYQBs0QMygOegQIARBp","date":"0006-06-07","description":".","id":"8dca72c4-f4fe-45fb-8353-dfd0012615dd"},{"id":"e1","title":"A dummy event","date":"2023-02-22","image":"https://blog.hubspot.de/hubfs/Germany/Blog_images/Optimize_Marketing%20Events%20DACH%202021.jpg","description":"Join this amazing event and connect with fellow developers."}]}